lpd8/__init__.py
lpd8/dispatcher.py
lpd8/knobs.py
lpd8/lpd8.py
lpd8/pads.py
lpd8/pgm_chg.py
lpd8/programs.py
lpd8/subscriber.py
lpd8-1.1.1.dist-info/LICENSE
lpd8-1.1.1.dist-info/METADATA
lpd8-1.1.1.dist-info/WHEEL
lpd8-1.1.1.dist-info/top_level.txt
lpd8-1.1.1.dist-info/RECORD
