Metadata-Version: 2.1
Name: lpd8
Version: 1.1.1
Summary: A Python library to drive an AKAI LPD8 pad controller
Home-page: https://github.com/zetof/LPD8
Author: Christophe Bury
Author-email: zetof@zetof.net
License: UNKNOWN
Platform: UNKNOWN
Classifier: Programming Language :: Python :: 3
Classifier: License :: OSI Approved :: MIT License
Classifier: Operating System :: OS Independent
Requires-Python: >=3.6
Requires-Dist: python-rtmidi
